contrast_fireball/__init__.py
contrast_fireball/libs/libfireball_c.dylib
contrast_fireball/libs/.gitignore
contrast_fireball-0.1.22.dist-info/RECORD
contrast_fireball-0.1.22.dist-info/WHEEL
contrast_fireball-0.1.22.dist-info/top_level.txt
contrast_fireball-0.1.22.dist-info/METADATA
contrast_fireball-0.1.22.dist-info/licenses/LICENSE
