Metadata-Version: 2.4
Name: contrast-fireball
Version: 0.1.22
Summary: Python interface to the shared Contrast Fireball library
Author-email: "Contrast Security, Inc." <python@contrastsecurity.com>
License: Copyright: 2024 Contrast Security, Inc
Project-URL: homepage, https://www.contrastsecurity.com
Project-URL: support, https://support.contrastsecurity.com
Classifier: Programming Language :: Rust
Classifier: Programming Language :: Python :: Implementation :: CPython
Classifier: Programming Language :: Python :: 3
Requires-Python: >=3.9
License-File: LICENSE
Dynamic: license-file
